open_tool_server/__init__.py
open_tool_server/_version.py
open_tool_server/mcp.py
open_tool_server/root.py
open_tool_server/tools.py
open_tool_server/auth/__init__.py
open_tool_server/auth/exceptions.py
open_tool_server/auth/middleware.py
open_tool_server/auth/types.py
open_tool_server-0.0.2.dist-info/METADATA
open_tool_server-0.0.2.dist-info/WHEEL
open_tool_server-0.0.2.dist-info/RECORD
